[
    {
        "id": "-7360338371572637187",
        "title": "MERN Stack Developer",
        "company": "WebCastle Media Pvt Ltd.",
        "location": "KL, IN",
        "date_posted": "2026-01-06",
        "found_at": "2026-01-06 06:46",
        "job_url": "https://in.indeed.com/viewjob?jk=a1420d1a1ff3ee4e",
        "site": "indeed",
        "analysis": {
            "is_suitable": true,
            "match_score": 28,
            "share_message": "Hey! Found this job: MERN Stack Developer at WebCastle Media Pvt Ltd.. Check it out!"
        }
    },
    {
        "id": "2574773643522814663",
        "title": "ReactJS Developer",
        "company": "Prodigy Placement LLP",
        "location": "GJ, IN",
        "date_posted": "2026-01-06",
        "found_at": "2026-01-06 06:46",
        "job_url": "https://in.indeed.com/viewjob?jk=648bea5ea4b8285b",
        "site": "indeed",
        "analysis": {
            "is_suitable": true,
            "match_score": 91,
            "share_message": "Hey! Found this job: ReactJS Developer at Prodigy Placement LLP. Check it out!"
        }
    },
    {
        "id": "-7162226748244981200",
        "title": "React js developer",
        "company": "Tata Consultancy Services",
        "location": "Mumbai, Maharashtra, India",
        "date_posted": "Unknown",
        "found_at": "2026-01-06 06:46",
        "job_url": "https://www.linkedin.com/jobs/view/4330513635",
        "site": "linkedin",
        "analysis": {
            "is_suitable": true,
            "match_score": 20,
            "share_message": "Hey! Found this job: React js developer at Tata Consultancy Services. Check it out!"
        }
    },
    {
        "id": "5304243378078944822",
        "title": "React Developer: Create World-Class Web Experiences at Scale",
        "company": "Mindstix Software Labs",
        "location": "Pune, Maharashtra, India",
        "date_posted": "Unknown",
        "found_at": "2026-01-06 06:46",
        "job_url": "https://www.linkedin.com/jobs/view/4354569786",
        "site": "linkedin",
        "analysis": {
            "is_suitable": true,
            "match_score": 20,
            "share_message": "Hey! Found this job: React Developer: Create World-Class Web Experiences at Scale at Mindstix Software Labs. Check it out!"
        }
    },
    {
        "id": "-2304613983788431815",
        "title": ".NET Core Developer ( Experienced )",
        "company": "DB Vertex Technologies",
        "location": "MP, IN",
        "date_posted": "2026-01-06",
        "found_at": "2026-01-06 06:46",
        "job_url": "https://in.indeed.com/viewjob?jk=a76e19ce935f20a1",
        "site": "indeed",
        "analysis": {
            "is_suitable": true,
            "match_score": 42,
            "share_message": "Hey! Found this job: .NET Core Developer ( Experienced ) at DB Vertex Technologies. Check it out!"
        }
    },
    {
        "id": "-8153135456803039575",
        "title": "Frontend Developer (React Js)",
        "company": "Nuarsh TECHSERVE",
        "location": "MP, IN",
        "date_posted": "2026-01-06",
        "found_at": "2026-01-06 05:32",
        "job_url": "https://in.indeed.com/viewjob?jk=9809c3f74558b11c",
        "site": "indeed",
        "analysis": {
            "is_suitable": true,
            "match_score": 62,
            "share_message": "Hey! Found this job: Frontend Developer (React Js) at Nuarsh TECHSERVE. Check it out!"
        }
    },
    {
        "id": "-1726532340437320622",
        "title": "Front-End Developer Intern (HTML, CSS, JavaScript, React))",
        "company": "Skillfied Mentor Jobs",
        "location": "",
        "date_posted": "Unknown",
        "found_at": "2026-01-06 05:32",
        "job_url": "https://www.linkedin.com/jobs/view/4354519798",
        "site": "linkedin",
        "analysis": {
            "is_suitable": true,
            "match_score": 20,
            "share_message": "Hey! Found this job: Front-End Developer Intern (HTML, CSS, JavaScript, React)) at Skillfied Mentor Jobs. Check it out!"
        }
    },
    {
        "id": "3205094071405772356",
        "title": "React js developer",
        "company": "Tata Consultancy Services",
        "location": "Mumbai, Maharashtra, India",
        "date_posted": "Unknown",
        "found_at": "2026-01-06 05:32",
        "job_url": "https://www.linkedin.com/jobs/view/4330513635",
        "site": "linkedin",
        "analysis": {
            "is_suitable": true,
            "match_score": 20,
            "share_message": "Hey! Found this job: React js developer at Tata Consultancy Services. Check it out!"
        }
    },
    {
        "id": "-5874087035417309103",
        "title": "React.js developer",
        "company": "People Prime Worldwide",
        "location": "Pune, Maharashtra, India",
        "date_posted": "Unknown",
        "found_at": "2026-01-06 05:32",
        "job_url": "https://www.linkedin.com/jobs/view/4330413616",
        "site": "linkedin",
        "analysis": {
            "is_suitable": true,
            "match_score": 20,
            "share_message": "Hey! Found this job: React.js developer at People Prime Worldwide. Check it out!"
        }
    },
    {
        "id": "-9030001054765328300",
        "title": "Frontend Developer (React Js)",
        "company": "Nuarsh TECHSERVE",
        "location": "MP, IN",
        "date_posted": "2026-01-06",
        "found_at": "2026-01-06 04:05",
        "job_url": "https://in.indeed.com/viewjob?jk=9809c3f74558b11c",
        "site": "indeed",
        "analysis": {
            "is_suitable": true,
            "match_score": 62,
            "share_message": "Hey! Found this job: Frontend Developer (React Js) at Nuarsh TECHSERVE. Check it out!"
        }
    },
    {
        "id": "-6678039823248482752",
        "title": "Software Developers (Java/Python/ReactJS/Atlassian JIRA)",
        "company": "Infosys",
        "location": "Bengaluru East, Karnataka, India",
        "date_posted": "Unknown",
        "found_at": "2026-01-06 04:05",
        "job_url": "https://www.linkedin.com/jobs/view/4330412573",
        "site": "linkedin",
        "analysis": {
            "is_suitable": true,
            "match_score": 20,
            "share_message": "Hey! Found this job: Software Developers (Java/Python/ReactJS/Atlassian JIRA) at Infosys. Check it out!"
        }
    },
    {
        "id": "-298628056385494044",
        "title": "Front-End Developer Intern (HTML, CSS, JavaScript, React))",
        "company": "Skillfied Mentor Jobs",
        "location": "",
        "date_posted": "Unknown",
        "found_at": "2026-01-06 04:05",
        "job_url": "https://www.linkedin.com/jobs/view/4354519798",
        "site": "linkedin",
        "analysis": {
            "is_suitable": true,
            "match_score": 20,
            "share_message": "Hey! Found this job: Front-End Developer Intern (HTML, CSS, JavaScript, React)) at Skillfied Mentor Jobs. Check it out!"
        }
    },
    {
        "id": "-3132036891725644276",
        "title": "Software Developers (Java/Python/ReactJS/Atlassian JIRA)",
        "company": "Infosys",
        "location": "Bengaluru East, Karnataka, India",
        "date_posted": "Unknown",
        "found_at": "2026-01-06 02:50",
        "job_url": "https://www.linkedin.com/jobs/view/4330412573",
        "site": "linkedin",
        "analysis": {
            "is_suitable": true,
            "match_score": 20,
            "share_message": "Hey! Found this job: Software Developers (Java/Python/ReactJS/Atlassian JIRA) at Infosys. Check it out!"
        }
    },
    {
        "id": "-6058291925715955029",
        "title": "Aertrip - React.js Developer - Javascript",
        "company": "Aertrip",
        "location": "",
        "date_posted": "Unknown",
        "found_at": "2026-01-06 02:50",
        "job_url": "https://www.linkedin.com/jobs/view/4358260283",
        "site": "linkedin",
        "analysis": {
            "is_suitable": true,
            "match_score": 20,
            "share_message": "Hey! Found this job: Aertrip - React.js Developer - Javascript at Aertrip. Check it out!"
        }
    },
    {
        "id": "-216280389731323596",
        "title": "React Ja Developer",
        "company": "Hirenza",
        "location": "",
        "date_posted": "Unknown",
        "found_at": "2026-01-06 02:50",
        "job_url": "https://www.linkedin.com/jobs/view/4354636106",
        "site": "linkedin",
        "analysis": {
            "is_suitable": true,
            "match_score": 20,
            "share_message": "Hey! Found this job: React Ja Developer at Hirenza. Check it out!"
        }
    },
    {
        "id": "-8711733362145836590",
        "title": "Front-End Developer Intern (HTML, CSS, JavaScript, React))",
        "company": "Skillfied Mentor Jobs",
        "location": "",
        "date_posted": "Unknown",
        "found_at": "2026-01-06 02:50",
        "job_url": "https://www.linkedin.com/jobs/view/4354519798",
        "site": "linkedin",
        "analysis": {
            "is_suitable": true,
            "match_score": 20,
            "share_message": "Hey! Found this job: Front-End Developer Intern (HTML, CSS, JavaScript, React)) at Skillfied Mentor Jobs. Check it out!"
        }
    }
]