[
    {
        "id": "6254391882439060766",
        "title": "Engineer 2, Software Development & Engineering",
        "company": "Comcast",
        "location": "TN, IN",
        "date_posted": "2026-01-06",
        "found_at": "04:06",
        "job_url": "https://in.indeed.com/viewjob?jk=b70839e0758b8776",
        "site": "indeed",
        "analysis": {
            "is_suitable": true,
            "match_score": 14,
            "share_message": "Hey! Found this job: Engineer 2, Software Development & Engineering at Comcast. Check it out!"
        }
    },
    {
        "id": "4042286637126615789",
        "title": "Engineer 2, Engineering Operations",
        "company": "Comcast",
        "location": "TN, IN",
        "date_posted": "2026-01-05",
        "found_at": "04:06",
        "job_url": "https://in.indeed.com/viewjob?jk=3971c9969a550427",
        "site": "indeed",
        "analysis": {
            "is_suitable": true,
            "match_score": 14,
            "share_message": "Hey! Found this job: Engineer 2, Engineering Operations at Comcast. Check it out!"
        }
    },
    {
        "id": "-4662722432335712010",
        "title": "Full Stack Developer",
        "company": "Call The Team",
        "location": "TN, IN",
        "date_posted": "2026-01-06",
        "found_at": "04:06",
        "job_url": "https://in.indeed.com/viewjob?jk=7b67415f97224406",
        "site": "indeed",
        "analysis": {
            "is_suitable": true,
            "match_score": 28,
            "share_message": "Hey! Found this job: Full Stack Developer at Call The Team. Check it out!"
        }
    },
    {
        "id": "9028734221056663339",
        "title": ".NET Core, ReactJS Developer",
        "company": "Concentrix",
        "location": "IN",
        "date_posted": "2026-01-06",
        "found_at": "04:06",
        "job_url": "https://in.indeed.com/viewjob?jk=d9b4e55cfab85600",
        "site": "indeed",
        "analysis": {
            "is_suitable": true,
            "match_score": 62,
            "share_message": "Hey! Found this job: .NET Core, ReactJS Developer at Concentrix. Check it out!"
        }
    },
    {
        "id": "-9125716773849391506",
        "title": "Junior Backend Developer",
        "company": "Sanguine Blue Business Solution",
        "location": "TN, IN",
        "date_posted": "2026-01-06",
        "found_at": "04:06",
        "job_url": "https://in.indeed.com/viewjob?jk=8d716d0d6c9622a0",
        "site": "indeed",
        "analysis": {
            "is_suitable": true,
            "match_score": 14,
            "share_message": "Hey! Found this job: Junior Backend Developer at Sanguine Blue Business Solution. Check it out!"
        }
    },
    {
        "id": "2550588395549893634",
        "title": "Full Stack Developer - Associate 2",
        "company": "RSM",
        "location": "TS, IN",
        "date_posted": "2026-01-06",
        "found_at": "04:06",
        "job_url": "https://in.indeed.com/viewjob?jk=5048435bede8692b",
        "site": "indeed",
        "analysis": {
            "is_suitable": true,
            "match_score": 71,
            "share_message": "Hey! Found this job: Full Stack Developer - Associate 2 at RSM. Check it out!"
        }
    },
    {
        "id": "-3361906856200332133",
        "title": "Software Developer",
        "company": "Salescom Services",
        "location": "WB, IN",
        "date_posted": "2026-01-06",
        "found_at": "04:06",
        "job_url": "https://in.indeed.com/viewjob?jk=b47b5a4275772500",
        "site": "indeed",
        "analysis": {
            "is_suitable": true,
            "match_score": 57,
            "share_message": "Hey! Found this job: Software Developer at Salescom Services. Check it out!"
        }
    },
    {
        "id": "9163051913116687830",
        "title": "MERN Stack Developer",
        "company": "Podium systems Pvt. Ltd",
        "location": "MP, IN",
        "date_posted": "2026-01-06",
        "found_at": "04:06",
        "job_url": "https://in.indeed.com/viewjob?jk=70f0b6c4d0b57b11",
        "site": "indeed",
        "analysis": {
            "is_suitable": true,
            "match_score": 57,
            "share_message": "Hey! Found this job: MERN Stack Developer at Podium systems Pvt. Ltd. Check it out!"
        }
    },
    {
        "id": "-2018220158711271152",
        "title": "Developer",
        "company": "Standard Chartered Bank",
        "location": "KA, IN",
        "date_posted": "2026-01-06",
        "found_at": "04:06",
        "job_url": "https://in.indeed.com/viewjob?jk=e4607df7a344c36e",
        "site": "indeed",
        "analysis": {
            "is_suitable": true,
            "match_score": 14,
            "share_message": "Hey! Found this job: Developer at Standard Chartered Bank. Check it out!"
        }
    },
    {
        "id": "8721689936776825666",
        "title": "Jr. MERN Stack Developer",
        "company": "FODDU- Website design and development",
        "location": "MP, IN",
        "date_posted": "2026-01-06",
        "found_at": "04:06",
        "job_url": "https://in.indeed.com/viewjob?jk=40890122b1eb7cb8",
        "site": "indeed",
        "analysis": {
            "is_suitable": true,
            "match_score": 28,
            "share_message": "Hey! Found this job: Jr. MERN Stack Developer at FODDU- Website design and development. Check it out!"
        }
    },
    {
        "id": "-7388968079004542961",
        "title": "Full Stack Developer",
        "company": "Cozmotec",
        "location": "MP, IN",
        "date_posted": "2026-01-06",
        "found_at": "04:06",
        "job_url": "https://in.indeed.com/viewjob?jk=d938782acd042f73",
        "site": "indeed",
        "analysis": {
            "is_suitable": true,
            "match_score": 71,
            "share_message": "Hey! Found this job: Full Stack Developer at Cozmotec. Check it out!"
        }
    },
    {
        "id": "6342519677580785627",
        "title": "Frontend Developer (React.js)",
        "company": "Weekday AI (YC W21)",
        "location": "Gurugram, Haryana, India",
        "date_posted": "Unknown",
        "found_at": "04:06",
        "job_url": "https://www.linkedin.com/jobs/view/4358272165",
        "site": "linkedin",
        "analysis": {
            "is_suitable": true,
            "match_score": 20,
            "share_message": "Hey! Found this job: Frontend Developer (React.js) at Weekday AI (YC W21). Check it out!"
        }
    },
    {
        "id": "-3083230967864442056",
        "title": "Frontend Developer (React.js)",
        "company": "Weekday AI (YC W21)",
        "location": "Delhi, India",
        "date_posted": "Unknown",
        "found_at": "04:06",
        "job_url": "https://www.linkedin.com/jobs/view/4358330896",
        "site": "linkedin",
        "analysis": {
            "is_suitable": true,
            "match_score": 20,
            "share_message": "Hey! Found this job: Frontend Developer (React.js) at Weekday AI (YC W21). Check it out!"
        }
    },
    {
        "id": "-6487851766034164926",
        "title": "Frontend Developer (React.js)",
        "company": "Weekday AI (YC W21)",
        "location": "Noida, Uttar Pradesh, India",
        "date_posted": "Unknown",
        "found_at": "04:06",
        "job_url": "https://www.linkedin.com/jobs/view/4358320938",
        "site": "linkedin",
        "analysis": {
            "is_suitable": true,
            "match_score": 20,
            "share_message": "Hey! Found this job: Frontend Developer (React.js) at Weekday AI (YC W21). Check it out!"
        }
    },
    {
        "id": "-8449184435064175950",
        "title": "React.js Developer",
        "company": "Concentrix",
        "location": "Bengaluru, Karnataka, India",
        "date_posted": "Unknown",
        "found_at": "04:06",
        "job_url": "https://www.linkedin.com/jobs/view/4351159810",
        "site": "linkedin",
        "analysis": {
            "is_suitable": true,
            "match_score": 20,
            "share_message": "Hey! Found this job: React.js Developer at Concentrix. Check it out!"
        }
    },
    {
        "id": "1339591382185004773",
        "title": "React Developer Intern",
        "company": "Skillzenloop",
        "location": "",
        "date_posted": "Unknown",
        "found_at": "04:06",
        "job_url": "https://www.linkedin.com/jobs/view/4351229519",
        "site": "linkedin",
        "analysis": {
            "is_suitable": true,
            "match_score": 20,
            "share_message": "Hey! Found this job: React Developer Intern at Skillzenloop. Check it out!"
        }
    },
    {
        "id": "7569533078100222878",
        "title": "Frontend Developer (React.js)",
        "company": "DIGIDEL SOLUTIONS",
        "location": "Delhi, India",
        "date_posted": "Unknown",
        "found_at": "04:06",
        "job_url": "https://www.linkedin.com/jobs/view/4358341237",
        "site": "linkedin",
        "analysis": {
            "is_suitable": true,
            "match_score": 20,
            "share_message": "Hey! Found this job: Frontend Developer (React.js) at DIGIDEL SOLUTIONS. Check it out!"
        }
    },
    {
        "id": "-6889756898488531796",
        "title": "React js developer",
        "company": "Tata Consultancy Services",
        "location": "Mumbai, Maharashtra, India",
        "date_posted": "Unknown",
        "found_at": "04:06",
        "job_url": "https://www.linkedin.com/jobs/view/4330513635",
        "site": "linkedin",
        "analysis": {
            "is_suitable": true,
            "match_score": 20,
            "share_message": "Hey! Found this job: React js developer at Tata Consultancy Services. Check it out!"
        }
    },
    {
        "id": "-8708641724984067811",
        "title": "ReactJS Developer",
        "company": "Sketch Brahma Technologies",
        "location": "Bengaluru, Karnataka, India",
        "date_posted": "Unknown",
        "found_at": "04:06",
        "job_url": "https://www.linkedin.com/jobs/view/4330425410",
        "site": "linkedin",
        "analysis": {
            "is_suitable": true,
            "match_score": 20,
            "share_message": "Hey! Found this job: ReactJS Developer at Sketch Brahma Technologies. Check it out!"
        }
    },
    {
        "id": "-6765822344160605158",
        "title": "React Developer: Create World-Class Web Experiences at Scale",
        "company": "Mindstix Software Labs",
        "location": "Pune, Maharashtra, India",
        "date_posted": "Unknown",
        "found_at": "04:06",
        "job_url": "https://www.linkedin.com/jobs/view/4354569786",
        "site": "linkedin",
        "analysis": {
            "is_suitable": true,
            "match_score": 20,
            "share_message": "Hey! Found this job: React Developer: Create World-Class Web Experiences at Scale at Mindstix Software Labs. Check it out!"
        }
    },
    {
        "id": "-5725280348238793980",
        "title": "React Developer",
        "company": "Hirenza",
        "location": "",
        "date_posted": "Unknown",
        "found_at": "04:06",
        "job_url": "https://www.linkedin.com/jobs/view/4358236752",
        "site": "linkedin",
        "analysis": {
            "is_suitable": true,
            "match_score": 20,
            "share_message": "Hey! Found this job: React Developer at Hirenza. Check it out!"
        }
    },
    {
        "id": "-2906949542662409706",
        "title": "Front-End Developer Intern (HTML, CSS, JavaScript, React))",
        "company": "Skillfied Mentor Jobs",
        "location": "",
        "date_posted": "Unknown",
        "found_at": "04:06",
        "job_url": "https://www.linkedin.com/jobs/view/4358157575",
        "site": "linkedin",
        "analysis": {
            "is_suitable": true,
            "match_score": 20,
            "share_message": "Hey! Found this job: Front-End Developer Intern (HTML, CSS, JavaScript, React)) at Skillfied Mentor Jobs. Check it out!"
        }
    },
    {
        "id": "-3986614011913180941",
        "title": "UI/UX Designer (Figma Expert)",
        "company": "Gomahamaya",
        "location": "BR, IN",
        "date_posted": "2026-01-06",
        "found_at": "04:06",
        "job_url": "https://in.indeed.com/viewjob?jk=bea6bf33f37b13ef",
        "site": "indeed",
        "analysis": {
            "is_suitable": true,
            "match_score": 28,
            "share_message": "Hey! Found this job: UI/UX Designer (Figma Expert) at Gomahamaya. Check it out!"
        }
    },
    {
        "id": "-5207066803050581800",
        "title": "Full Stack Developer (Fresher)",
        "company": "Sioniq",
        "location": "KL, IN",
        "date_posted": "2026-01-06",
        "found_at": "04:06",
        "job_url": "https://in.indeed.com/viewjob?jk=132ce1dca3ce7cde",
        "site": "indeed",
        "analysis": {
            "is_suitable": true,
            "match_score": 77,
            "share_message": "Hey! Found this job: Full Stack Developer (Fresher) at Sioniq. Check it out!"
        }
    },
    {
        "id": "-2615633287628666092",
        "title": "Full Stack Developer Intern",
        "company": "Accusoil Agri technologies PVT LTD",
        "location": "RJ, IN",
        "date_posted": "2026-01-06",
        "found_at": "04:06",
        "job_url": "https://in.indeed.com/viewjob?jk=70a9de8445067f42",
        "site": "indeed",
        "analysis": {
            "is_suitable": true,
            "match_score": 28,
            "share_message": "Hey! Found this job: Full Stack Developer Intern at Accusoil Agri technologies PVT LTD. Check it out!"
        }
    },
    {
        "id": "-5740219472200805573",
        "title": "AI-Augmented Software Developer (1-3 Years ) (Mumbai)",
        "company": "Wama Technology",
        "location": "MH, IN",
        "date_posted": "2026-01-06",
        "found_at": "04:06",
        "job_url": "https://in.indeed.com/viewjob?jk=925d0ed092cf659c",
        "site": "indeed",
        "analysis": {
            "is_suitable": true,
            "match_score": 57,
            "share_message": "Hey! Found this job: AI-Augmented Software Developer (1-3 Years ) (Mumbai) at Wama Technology. Check it out!"
        }
    },
    {
        "id": "6028385681517462066",
        "title": "Assistant Full Stack Developer",
        "company": "EasyLauncher",
        "location": "UP, IN",
        "date_posted": "2026-01-06",
        "found_at": "04:06",
        "job_url": "https://in.indeed.com/viewjob?jk=cdc7cecd603387b2",
        "site": "indeed",
        "analysis": {
            "is_suitable": true,
            "match_score": 71,
            "share_message": "Hey! Found this job: Assistant Full Stack Developer at EasyLauncher. Check it out!"
        }
    },
    {
        "id": "5879300306336303847",
        "title": "Dot Net Developer",
        "company": "Ciya Technologies",
        "location": "OR, IN",
        "date_posted": "2026-01-06",
        "found_at": "04:06",
        "job_url": "https://in.indeed.com/viewjob?jk=252ad2b45a2c9b80",
        "site": "indeed",
        "analysis": {
            "is_suitable": true,
            "match_score": 57,
            "share_message": "Hey! Found this job: Dot Net Developer at Ciya Technologies. Check it out!"
        }
    },
    {
        "id": "-6151701045778795922",
        "title": "PHP Laravel Developer",
        "company": "Jangras Corporation",
        "location": "HR, IN",
        "date_posted": "2026-01-06",
        "found_at": "04:06",
        "job_url": "https://in.indeed.com/viewjob?jk=27e15bfded0f6e78",
        "site": "indeed",
        "analysis": {
            "is_suitable": true,
            "match_score": 57,
            "share_message": "Hey! Found this job: PHP Laravel Developer at Jangras Corporation. Check it out!"
        }
    },
    {
        "id": "-3003438628663362670",
        "title": "Full Stack Python Developer",
        "company": "Hashtechy",
        "location": "GJ, IN",
        "date_posted": "2026-01-06",
        "found_at": "04:06",
        "job_url": "https://in.indeed.com/viewjob?jk=5d6ac5d4c0e5755c",
        "site": "indeed",
        "analysis": {
            "is_suitable": true,
            "match_score": 77,
            "share_message": "Hey! Found this job: Full Stack Python Developer at Hashtechy. Check it out!"
        }
    },
    {
        "id": "-1219953424482139130",
        "title": ".NET Core Developer ( Experienced )",
        "company": "DB Vertex Technologies",
        "location": "MP, IN",
        "date_posted": "2026-01-06",
        "found_at": "04:06",
        "job_url": "https://in.indeed.com/viewjob?jk=a76e19ce935f20a1",
        "site": "indeed",
        "analysis": {
            "is_suitable": true,
            "match_score": 42,
            "share_message": "Hey! Found this job: .NET Core Developer ( Experienced ) at DB Vertex Technologies. Check it out!"
        }
    },
    {
        "id": "-6783260749688074227",
        "title": "Software Dev Engineer I, Amazon University Talent Acquisition",
        "company": "Amazon.com",
        "location": "DL, IN",
        "date_posted": "2025-11-18",
        "found_at": "04:06",
        "job_url": "https://in.indeed.com/viewjob?jk=07a77e5dbf764d1b",
        "site": "indeed",
        "analysis": {
            "is_suitable": true,
            "match_score": 14,
            "share_message": "Hey! Found this job: Software Dev Engineer I, Amazon University Talent Acquisition at Amazon.com. Check it out!"
        }
    },
    {
        "id": "-6876278539420095813",
        "title": "Software Dev Engineer I, Amazon University Talent Acquisition",
        "company": "Amazon.com",
        "location": "TN, IN",
        "date_posted": "2025-11-18",
        "found_at": "04:06",
        "job_url": "https://in.indeed.com/viewjob?jk=627c73257c148c3c",
        "site": "indeed",
        "analysis": {
            "is_suitable": true,
            "match_score": 14,
            "share_message": "Hey! Found this job: Software Dev Engineer I, Amazon University Talent Acquisition at Amazon.com. Check it out!"
        }
    },
    {
        "id": "3442522274723396242",
        "title": "Software Dev Engineer I, Amazon University Talent Acquisition",
        "company": "Amazon.com",
        "location": "TS, IN",
        "date_posted": "2025-11-18",
        "found_at": "04:06",
        "job_url": "https://in.indeed.com/viewjob?jk=0bab7c9825ef4fa9",
        "site": "indeed",
        "analysis": {
            "is_suitable": true,
            "match_score": 14,
            "share_message": "Hey! Found this job: Software Dev Engineer I, Amazon University Talent Acquisition at Amazon.com. Check it out!"
        }
    },
    {
        "id": "1444348272796393690",
        "title": "Software Dev Engineer I, Amazon University Talent Acquisition",
        "company": "Amazon.com",
        "location": "MH, IN",
        "date_posted": "2025-11-18",
        "found_at": "04:06",
        "job_url": "https://in.indeed.com/viewjob?jk=5cb234f27c30ad57",
        "site": "indeed",
        "analysis": {
            "is_suitable": true,
            "match_score": 14,
            "share_message": "Hey! Found this job: Software Dev Engineer I, Amazon University Talent Acquisition at Amazon.com. Check it out!"
        }
    },
    {
        "id": "-7237055913762436574",
        "title": "Software Dev Engineer I, Amazon University Talent Acquisition",
        "company": "Amazon.com",
        "location": "KA, IN",
        "date_posted": "2025-11-18",
        "found_at": "04:06",
        "job_url": "https://in.indeed.com/viewjob?jk=fc430075373f58a7",
        "site": "indeed",
        "analysis": {
            "is_suitable": true,
            "match_score": 14,
            "share_message": "Hey! Found this job: Software Dev Engineer I, Amazon University Talent Acquisition at Amazon.com. Check it out!"
        }
    },
    {
        "id": "4596759926451073397",
        "title": "Software Dev Engineer I, Amazon University Talent Acquisition",
        "company": "Amazon.com",
        "location": "TS, IN",
        "date_posted": "2025-10-03",
        "found_at": "04:06",
        "job_url": "https://in.indeed.com/viewjob?jk=de64639c77d5d748",
        "site": "indeed",
        "analysis": {
            "is_suitable": true,
            "match_score": 14,
            "share_message": "Hey! Found this job: Software Dev Engineer I, Amazon University Talent Acquisition at Amazon.com. Check it out!"
        }
    },
    {
        "id": "6656728192162976016",
        "title": "Software Dev Engineer I, Amazon University Talent Acquisition",
        "company": "Amazon.com",
        "location": "TN, IN",
        "date_posted": "2025-09-30",
        "found_at": "04:06",
        "job_url": "https://in.indeed.com/viewjob?jk=f3497a08a2587179",
        "site": "indeed",
        "analysis": {
            "is_suitable": true,
            "match_score": 14,
            "share_message": "Hey! Found this job: Software Dev Engineer I, Amazon University Talent Acquisition at Amazon.com. Check it out!"
        }
    },
    {
        "id": "3617992930331553054",
        "title": "Software Dev Engineer I, Amazon University Talent Acquisition",
        "company": "Amazon.com",
        "location": "DL, IN",
        "date_posted": "2025-09-30",
        "found_at": "04:06",
        "job_url": "https://in.indeed.com/viewjob?jk=bf6fbb1f611b0fd5",
        "site": "indeed",
        "analysis": {
            "is_suitable": true,
            "match_score": 14,
            "share_message": "Hey! Found this job: Software Dev Engineer I, Amazon University Talent Acquisition at Amazon.com. Check it out!"
        }
    },
    {
        "id": "-5760385319490102536",
        "title": "Software Dev Engineer I, Amazon University Talent Acquisition",
        "company": "Amazon.com",
        "location": "TS, IN",
        "date_posted": "2025-09-30",
        "found_at": "04:06",
        "job_url": "https://in.indeed.com/viewjob?jk=9dfe4f76630e17ac",
        "site": "indeed",
        "analysis": {
            "is_suitable": true,
            "match_score": 14,
            "share_message": "Hey! Found this job: Software Dev Engineer I, Amazon University Talent Acquisition at Amazon.com. Check it out!"
        }
    },
    {
        "id": "-4281574478542077052",
        "title": "Software Dev Engineer I, Amazon University Talent Acquisition",
        "company": "Amazon.com",
        "location": "KA, IN",
        "date_posted": "2025-09-30",
        "found_at": "04:06",
        "job_url": "https://in.indeed.com/viewjob?jk=29e96f7f829e04d4",
        "site": "indeed",
        "analysis": {
            "is_suitable": true,
            "match_score": 14,
            "share_message": "Hey! Found this job: Software Dev Engineer I, Amazon University Talent Acquisition at Amazon.com. Check it out!"
        }
    },
    {
        "id": "2350431721605068891",
        "title": "Software Dev Engineer I, Amazon University Talent Acquisition",
        "company": "Amazon.com",
        "location": "TN, IN",
        "date_posted": "2025-06-23",
        "found_at": "04:06",
        "job_url": "https://in.indeed.com/viewjob?jk=bff26969a8395529",
        "site": "indeed",
        "analysis": {
            "is_suitable": true,
            "match_score": 14,
            "share_message": "Hey! Found this job: Software Dev Engineer I, Amazon University Talent Acquisition at Amazon.com. Check it out!"
        }
    },
    {
        "id": "-2906111113917094609",
        "title": "Software Dev Engineer I, Amazon University Talent Acquisition",
        "company": "Amazon.com",
        "location": "MH, IN",
        "date_posted": "2025-06-23",
        "found_at": "04:06",
        "job_url": "https://in.indeed.com/viewjob?jk=02127fa030d46275",
        "site": "indeed",
        "analysis": {
            "is_suitable": true,
            "match_score": 14,
            "share_message": "Hey! Found this job: Software Dev Engineer I, Amazon University Talent Acquisition at Amazon.com. Check it out!"
        }
    },
    {
        "id": "9119781456156298341",
        "title": "Software Dev Engineer I, Amazon University Talent Acquisition",
        "company": "Amazon.com",
        "location": "TS, IN",
        "date_posted": "2025-06-23",
        "found_at": "04:06",
        "job_url": "https://in.indeed.com/viewjob?jk=a28e41f94613b1fb",
        "site": "indeed",
        "analysis": {
            "is_suitable": true,
            "match_score": 14,
            "share_message": "Hey! Found this job: Software Dev Engineer I, Amazon University Talent Acquisition at Amazon.com. Check it out!"
        }
    },
    {
        "id": "-2151388544330748172",
        "title": "Software Dev Engineer I, Amazon University Talent Acquisition",
        "company": "Amazon.com",
        "location": "DL, IN",
        "date_posted": "2025-06-23",
        "found_at": "04:06",
        "job_url": "https://in.indeed.com/viewjob?jk=d3575ca06caef5ba",
        "site": "indeed",
        "analysis": {
            "is_suitable": true,
            "match_score": 14,
            "share_message": "Hey! Found this job: Software Dev Engineer I, Amazon University Talent Acquisition at Amazon.com. Check it out!"
        }
    },
    {
        "id": "-4752871068291816609",
        "title": "Software Dev Engineer I, Amazon University Talent Acquisition",
        "company": "Amazon.com",
        "location": "KA, IN",
        "date_posted": "2025-06-23",
        "found_at": "04:06",
        "job_url": "https://in.indeed.com/viewjob?jk=95366f34545c8575",
        "site": "indeed",
        "analysis": {
            "is_suitable": true,
            "match_score": 14,
            "share_message": "Hey! Found this job: Software Dev Engineer I, Amazon University Talent Acquisition at Amazon.com. Check it out!"
        }
    },
    {
        "id": "-8583175927715254233",
        "title": "Software Dev Engineer I, Amazon University Talent Acquisition",
        "company": "Amazon.com",
        "location": "DL, IN",
        "date_posted": "2025-03-24",
        "found_at": "04:06",
        "job_url": "https://in.indeed.com/viewjob?jk=26947f19e9d3a915",
        "site": "indeed",
        "analysis": {
            "is_suitable": true,
            "match_score": 14,
            "share_message": "Hey! Found this job: Software Dev Engineer I, Amazon University Talent Acquisition at Amazon.com. Check it out!"
        }
    },
    {
        "id": "4203782240700725978",
        "title": "Software Dev Engineer I, Amazon University Talent Acquisition",
        "company": "Amazon.com",
        "location": "KA, IN",
        "date_posted": "2025-03-24",
        "found_at": "04:06",
        "job_url": "https://in.indeed.com/viewjob?jk=3007bf9e2b628a3e",
        "site": "indeed",
        "analysis": {
            "is_suitable": true,
            "match_score": 14,
            "share_message": "Hey! Found this job: Software Dev Engineer I, Amazon University Talent Acquisition at Amazon.com. Check it out!"
        }
    },
    {
        "id": "-7831026333030967924",
        "title": "Software Dev Engineer I, Amazon University Talent Acquisition",
        "company": "Amazon.com",
        "location": "TS, IN",
        "date_posted": "2025-03-24",
        "found_at": "04:06",
        "job_url": "https://in.indeed.com/viewjob?jk=d1a12fedc50b3380",
        "site": "indeed",
        "analysis": {
            "is_suitable": true,
            "match_score": 14,
            "share_message": "Hey! Found this job: Software Dev Engineer I, Amazon University Talent Acquisition at Amazon.com. Check it out!"
        }
    },
    {
        "id": "7592441503606274702",
        "title": "Software Dev Engineer I, Amazon University Talent Acquisition",
        "company": "Amazon.com",
        "location": "MH, IN",
        "date_posted": "2025-03-24",
        "found_at": "04:06",
        "job_url": "https://in.indeed.com/viewjob?jk=031103dce8a70aba",
        "site": "indeed",
        "analysis": {
            "is_suitable": true,
            "match_score": 14,
            "share_message": "Hey! Found this job: Software Dev Engineer I, Amazon University Talent Acquisition at Amazon.com. Check it out!"
        }
    },
    {
        "id": "3390755620553440291",
        "title": "Software Dev Engineer I, Amazon University Talent Acquisition",
        "company": "Amazon.com",
        "location": "TN, IN",
        "date_posted": "2025-03-24",
        "found_at": "04:06",
        "job_url": "https://in.indeed.com/viewjob?jk=3d6bead3cc4403e2",
        "site": "indeed",
        "analysis": {
            "is_suitable": true,
            "match_score": 14,
            "share_message": "Hey! Found this job: Software Dev Engineer I, Amazon University Talent Acquisition at Amazon.com. Check it out!"
        }
    },
    {
        "id": "-3029085514269098112",
        "title": "Software Development Intern",
        "company": "Park Place Technologies India Private Li",
        "location": "TS, IN",
        "date_posted": "2026-01-06",
        "found_at": "04:06",
        "job_url": "https://in.indeed.com/viewjob?jk=522402ff0a92a5f5",
        "site": "indeed",
        "analysis": {
            "is_suitable": true,
            "match_score": 14,
            "share_message": "Hey! Found this job: Software Development Intern at Park Place Technologies India Private Li. Check it out!"
        }
    },
    {
        "id": "7334652550934524041",
        "title": "Python Software Developer Intern",
        "company": "Skillzenloop",
        "location": "",
        "date_posted": "Unknown",
        "found_at": "04:06",
        "job_url": "https://www.linkedin.com/jobs/view/4351219799",
        "site": "linkedin",
        "analysis": {
            "is_suitable": true,
            "match_score": 20,
            "share_message": "Hey! Found this job: Python Software Developer Intern at Skillzenloop. Check it out!"
        }
    },
    {
        "id": "-2974058008220482655",
        "title": "Dot Net Full Stack Developer - Position 4",
        "company": "DXC Technology",
        "location": "TN, IN",
        "date_posted": "2026-01-06",
        "found_at": "04:06",
        "job_url": "https://in.indeed.com/viewjob?jk=bb3ed705d4783024",
        "site": "indeed",
        "analysis": {
            "is_suitable": true,
            "match_score": 57,
            "share_message": "Hey! Found this job: Dot Net Full Stack Developer - Position 4 at DXC Technology. Check it out!"
        }
    },
    {
        "id": "-3503438509522141510",
        "title": "Dot Net Full stack Developer - Position 5",
        "company": "DXC Technology",
        "location": "TN, IN",
        "date_posted": "2026-01-06",
        "found_at": "04:06",
        "job_url": "https://in.indeed.com/viewjob?jk=614bbc10204f83e8",
        "site": "indeed",
        "analysis": {
            "is_suitable": true,
            "match_score": 57,
            "share_message": "Hey! Found this job: Dot Net Full stack Developer - Position 5 at DXC Technology. Check it out!"
        }
    },
    {
        "id": "-516607082427987649",
        "title": "Dot Net Full Stack developer - Position 1",
        "company": "DXC Technology",
        "location": "TN, IN",
        "date_posted": "2026-01-06",
        "found_at": "04:06",
        "job_url": "https://in.indeed.com/viewjob?jk=0d8b267269b5e1eb",
        "site": "indeed",
        "analysis": {
            "is_suitable": true,
            "match_score": 57,
            "share_message": "Hey! Found this job: Dot Net Full Stack developer - Position 1 at DXC Technology. Check it out!"
        }
    },
    {
        "id": "-2335621388354021182",
        "title": "Dot Net Full Stack Developer - Position 2",
        "company": "DXC Technology",
        "location": "TN, IN",
        "date_posted": "2026-01-06",
        "found_at": "04:06",
        "job_url": "https://in.indeed.com/viewjob?jk=d96d07c760ac57c2",
        "site": "indeed",
        "analysis": {
            "is_suitable": true,
            "match_score": 57,
            "share_message": "Hey! Found this job: Dot Net Full Stack Developer - Position 2 at DXC Technology. Check it out!"
        }
    },
    {
        "id": "883565827210627739",
        "title": "Software Engineering Associate Advisor - HIH - Evernorth",
        "company": "The Cigna Group",
        "location": "AP, IN",
        "date_posted": "2026-01-06",
        "found_at": "04:06",
        "job_url": "https://in.indeed.com/viewjob?jk=11ded95c1ae4fde9",
        "site": "indeed",
        "analysis": {
            "is_suitable": true,
            "match_score": 57,
            "share_message": "Hey! Found this job: Software Engineering Associate Advisor - HIH - Evernorth at The Cigna Group. Check it out!"
        }
    },
    {
        "id": "-5863824057442684861",
        "title": "Java Full Stack Developer-(Angular, Spring boot)",
        "company": "GlobalFoundries",
        "location": "KA, IN",
        "date_posted": "2026-01-06",
        "found_at": "04:06",
        "job_url": "https://in.indeed.com/viewjob?jk=efb746bda33d41b7",
        "site": "indeed",
        "analysis": {
            "is_suitable": true,
            "match_score": 28,
            "share_message": "Hey! Found this job: Java Full Stack Developer-(Angular, Spring boot) at GlobalFoundries. Check it out!"
        }
    },
    {
        "id": "-8226951241992654847",
        "title": "Associate software engineer (Angular, Spring boot/ Java)",
        "company": "NielsenIQ",
        "location": "TN, IN",
        "date_posted": "2026-01-06",
        "found_at": "04:06",
        "job_url": "https://in.indeed.com/viewjob?jk=2a5c2914570fa20b",
        "site": "indeed",
        "analysis": {
            "is_suitable": true,
            "match_score": 42,
            "share_message": "Hey! Found this job: Associate software engineer (Angular, Spring boot/ Java) at NielsenIQ. Check it out!"
        }
    },
    {
        "id": "3855211840460450700",
        "title": "Fullstack Engineer (NodeJs, React)",
        "company": "Fractal",
        "location": "Pune, Maharashtra, India",
        "date_posted": "Unknown",
        "found_at": "04:06",
        "job_url": "https://www.linkedin.com/jobs/view/4324302082",
        "site": "linkedin",
        "analysis": {
            "is_suitable": true,
            "match_score": 20,
            "share_message": "Hey! Found this job: Fullstack Engineer (NodeJs, React) at Fractal. Check it out!"
        }
    },
    {
        "id": "4030744394388146735",
        "title": "Frontend Developer - React.js/AngularJS",
        "company": "Aumni",
        "location": "Pune, Maharashtra, India",
        "date_posted": "Unknown",
        "found_at": "04:06",
        "job_url": "https://www.linkedin.com/jobs/view/4358256700",
        "site": "linkedin",
        "analysis": {
            "is_suitable": true,
            "match_score": 20,
            "share_message": "Hey! Found this job: Frontend Developer - React.js/AngularJS at Aumni. Check it out!"
        }
    },
    {
        "id": "2420114422898694522",
        "title": "Engineer 2, Software Development & Engineering",
        "company": "Comcast",
        "location": "TN, IN",
        "date_posted": "2026-01-06",
        "found_at": "02:13",
        "job_url": "https://in.indeed.com/viewjob?jk=b70839e0758b8776",
        "site": "indeed",
        "analysis": {
            "is_suitable": true,
            "match_score": 14,
            "share_message": "Hey! Found this job: Engineer 2, Software Development & Engineering at Comcast. Check it out!"
        }
    },
    {
        "id": "719563770404662464",
        "title": "Engineer 2, Engineering Operations",
        "company": "Comcast",
        "location": "TN, IN",
        "date_posted": "2026-01-05",
        "found_at": "02:13",
        "job_url": "https://in.indeed.com/viewjob?jk=3971c9969a550427",
        "site": "indeed",
        "analysis": {
            "is_suitable": true,
            "match_score": 14,
            "share_message": "Hey! Found this job: Engineer 2, Engineering Operations at Comcast. Check it out!"
        }
    },
    {
        "id": "916811874521953775",
        "title": "Full Stack Developer",
        "company": "Call The Team",
        "location": "TN, IN",
        "date_posted": "2026-01-06",
        "found_at": "02:13",
        "job_url": "https://in.indeed.com/viewjob?jk=7b67415f97224406",
        "site": "indeed",
        "analysis": {
            "is_suitable": true,
            "match_score": 28,
            "share_message": "Hey! Found this job: Full Stack Developer at Call The Team. Check it out!"
        }
    },
    {
        "id": "5820552373409898115",
        "title": ".NET Core, ReactJS Developer",
        "company": "Concentrix",
        "location": "IN",
        "date_posted": "2026-01-06",
        "found_at": "02:13",
        "job_url": "https://in.indeed.com/viewjob?jk=d9b4e55cfab85600",
        "site": "indeed",
        "analysis": {
            "is_suitable": true,
            "match_score": 62,
            "share_message": "Hey! Found this job: .NET Core, ReactJS Developer at Concentrix. Check it out!"
        }
    },
    {
        "id": "3288634192860750930",
        "title": "Junior Backend Developer",
        "company": "Sanguine Blue Business Solution",
        "location": "TN, IN",
        "date_posted": "2026-01-06",
        "found_at": "02:13",
        "job_url": "https://in.indeed.com/viewjob?jk=8d716d0d6c9622a0",
        "site": "indeed",
        "analysis": {
            "is_suitable": true,
            "match_score": 14,
            "share_message": "Hey! Found this job: Junior Backend Developer at Sanguine Blue Business Solution. Check it out!"
        }
    },
    {
        "id": "6642268391429574269",
        "title": "Full Stack Developer - Associate 2",
        "company": "RSM",
        "location": "TS, IN",
        "date_posted": "2026-01-06",
        "found_at": "02:13",
        "job_url": "https://in.indeed.com/viewjob?jk=5048435bede8692b",
        "site": "indeed",
        "analysis": {
            "is_suitable": true,
            "match_score": 71,
            "share_message": "Hey! Found this job: Full Stack Developer - Associate 2 at RSM. Check it out!"
        }
    },
    {
        "id": "6290973353488003930",
        "title": "Software Developer",
        "company": "Salescom Services",
        "location": "WB, IN",
        "date_posted": "2026-01-06",
        "found_at": "02:13",
        "job_url": "https://in.indeed.com/viewjob?jk=b47b5a4275772500",
        "site": "indeed",
        "analysis": {
            "is_suitable": true,
            "match_score": 57,
            "share_message": "Hey! Found this job: Software Developer at Salescom Services. Check it out!"
        }
    },
    {
        "id": "1660493132863762597",
        "title": "MERN Stack Developer",
        "company": "Podium systems Pvt. Ltd",
        "location": "MP, IN",
        "date_posted": "2026-01-06",
        "found_at": "02:13",
        "job_url": "https://in.indeed.com/viewjob?jk=70f0b6c4d0b57b11",
        "site": "indeed",
        "analysis": {
            "is_suitable": true,
            "match_score": 57,
            "share_message": "Hey! Found this job: MERN Stack Developer at Podium systems Pvt. Ltd. Check it out!"
        }
    },
    {
        "id": "1761874038451696558",
        "title": "Developer",
        "company": "Standard Chartered Bank",
        "location": "KA, IN",
        "date_posted": "2026-01-06",
        "found_at": "02:13",
        "job_url": "https://in.indeed.com/viewjob?jk=e4607df7a344c36e",
        "site": "indeed",
        "analysis": {
            "is_suitable": true,
            "match_score": 14,
            "share_message": "Hey! Found this job: Developer at Standard Chartered Bank. Check it out!"
        }
    },
    {
        "id": "-6579319775602092827",
        "title": "Jr. MERN Stack Developer",
        "company": "FODDU- Website design and development",
        "location": "MP, IN",
        "date_posted": "2026-01-06",
        "found_at": "02:13",
        "job_url": "https://in.indeed.com/viewjob?jk=40890122b1eb7cb8",
        "site": "indeed",
        "analysis": {
            "is_suitable": true,
            "match_score": 28,
            "share_message": "Hey! Found this job: Jr. MERN Stack Developer at FODDU- Website design and development. Check it out!"
        }
    },
    {
        "id": "7437536529131063051",
        "title": "Full Stack Developer",
        "company": "Cozmotec",
        "location": "MP, IN",
        "date_posted": "2026-01-06",
        "found_at": "02:13",
        "job_url": "https://in.indeed.com/viewjob?jk=d938782acd042f73",
        "site": "indeed",
        "analysis": {
            "is_suitable": true,
            "match_score": 71,
            "share_message": "Hey! Found this job: Full Stack Developer at Cozmotec. Check it out!"
        }
    },
    {
        "id": "7566408634918654249",
        "title": "Frontend Developer (React.js)",
        "company": "Weekday AI (YC W21)",
        "location": "Gurugram, Haryana, India",
        "date_posted": "Unknown",
        "found_at": "02:13",
        "job_url": "https://www.linkedin.com/jobs/view/4358272165",
        "site": "linkedin",
        "analysis": {
            "is_suitable": true,
            "match_score": 20,
            "share_message": "Hey! Found this job: Frontend Developer (React.js) at Weekday AI (YC W21). Check it out!"
        }
    },
    {
        "id": "8170511055408646233",
        "title": "Frontend Developer (React.js)",
        "company": "Weekday AI (YC W21)",
        "location": "Delhi, India",
        "date_posted": "Unknown",
        "found_at": "02:13",
        "job_url": "https://www.linkedin.com/jobs/view/4358330896",
        "site": "linkedin",
        "analysis": {
            "is_suitable": true,
            "match_score": 20,
            "share_message": "Hey! Found this job: Frontend Developer (React.js) at Weekday AI (YC W21). Check it out!"
        }
    },
    {
        "id": "-5010266976168581187",
        "title": "Frontend Developer (React.js)",
        "company": "Weekday AI (YC W21)",
        "location": "Noida, Uttar Pradesh, India",
        "date_posted": "Unknown",
        "found_at": "02:13",
        "job_url": "https://www.linkedin.com/jobs/view/4358320938",
        "site": "linkedin",
        "analysis": {
            "is_suitable": true,
            "match_score": 20,
            "share_message": "Hey! Found this job: Frontend Developer (React.js) at Weekday AI (YC W21). Check it out!"
        }
    },
    {
        "id": "3893780676325459577",
        "title": "React.js Developer",
        "company": "Concentrix",
        "location": "Bengaluru, Karnataka, India",
        "date_posted": "Unknown",
        "found_at": "02:13",
        "job_url": "https://www.linkedin.com/jobs/view/4351159810",
        "site": "linkedin",
        "analysis": {
            "is_suitable": true,
            "match_score": 20,
            "share_message": "Hey! Found this job: React.js Developer at Concentrix. Check it out!"
        }
    },
    {
        "id": "-412136259610761279",
        "title": "React Developer Intern",
        "company": "Skillzenloop",
        "location": "",
        "date_posted": "Unknown",
        "found_at": "02:13",
        "job_url": "https://www.linkedin.com/jobs/view/4351229519",
        "site": "linkedin",
        "analysis": {
            "is_suitable": true,
            "match_score": 20,
            "share_message": "Hey! Found this job: React Developer Intern at Skillzenloop. Check it out!"
        }
    },
    {
        "id": "-5270353088691502843",
        "title": "Frontend Developer (React.js)",
        "company": "DIGIDEL SOLUTIONS",
        "location": "Delhi, India",
        "date_posted": "Unknown",
        "found_at": "02:13",
        "job_url": "https://www.linkedin.com/jobs/view/4358341237",
        "site": "linkedin",
        "analysis": {
            "is_suitable": true,
            "match_score": 20,
            "share_message": "Hey! Found this job: Frontend Developer (React.js) at DIGIDEL SOLUTIONS. Check it out!"
        }
    },
    {
        "id": "-8793314231881071448",
        "title": "React js developer",
        "company": "Tata Consultancy Services",
        "location": "Mumbai, Maharashtra, India",
        "date_posted": "Unknown",
        "found_at": "02:13",
        "job_url": "https://www.linkedin.com/jobs/view/4330513635",
        "site": "linkedin",
        "analysis": {
            "is_suitable": true,
            "match_score": 20,
            "share_message": "Hey! Found this job: React js developer at Tata Consultancy Services. Check it out!"
        }
    },
    {
        "id": "6777190786063116435",
        "title": "ReactJS Developer",
        "company": "Sketch Brahma Technologies",
        "location": "Bengaluru, Karnataka, India",
        "date_posted": "Unknown",
        "found_at": "02:13",
        "job_url": "https://www.linkedin.com/jobs/view/4330425410",
        "site": "linkedin",
        "analysis": {
            "is_suitable": true,
            "match_score": 20,
            "share_message": "Hey! Found this job: ReactJS Developer at Sketch Brahma Technologies. Check it out!"
        }
    },
    {
        "id": "-4071816630459916325",
        "title": "React Developer: Create World-Class Web Experiences at Scale",
        "company": "Mindstix Software Labs",
        "location": "Pune, Maharashtra, India",
        "date_posted": "Unknown",
        "found_at": "02:13",
        "job_url": "https://www.linkedin.com/jobs/view/4354569786",
        "site": "linkedin",
        "analysis": {
            "is_suitable": true,
            "match_score": 20,
            "share_message": "Hey! Found this job: React Developer: Create World-Class Web Experiences at Scale at Mindstix Software Labs. Check it out!"
        }
    },
    {
        "id": "-8036150529763588448",
        "title": "ReactJs Developer",
        "company": "Viraaj HR Solutions Private Limited",
        "location": "Pune, Maharashtra, India",
        "date_posted": "Unknown",
        "found_at": "02:13",
        "job_url": "https://www.linkedin.com/jobs/view/4330515753",
        "site": "linkedin",
        "analysis": {
            "is_suitable": true,
            "match_score": 20,
            "share_message": "Hey! Found this job: ReactJs Developer at Viraaj HR Solutions Private Limited. Check it out!"
        }
    },
    {
        "id": "5443778698690072362",
        "title": "ReactJS Developer",
        "company": "Tata Consultancy Services",
        "location": "Chennai, Tamil Nadu, India",
        "date_posted": "Unknown",
        "found_at": "02:13",
        "job_url": "https://www.linkedin.com/jobs/view/4330485008",
        "site": "linkedin",
        "analysis": {
            "is_suitable": true,
            "match_score": 20,
            "share_message": "Hey! Found this job: ReactJS Developer at Tata Consultancy Services. Check it out!"
        }
    },
    {
        "id": "-2179611675087049520",
        "title": "React Developer",
        "company": "ProLegion",
        "location": "",
        "date_posted": "Unknown",
        "found_at": "02:13",
        "job_url": "https://www.linkedin.com/jobs/view/4358143097",
        "site": "linkedin",
        "analysis": {
            "is_suitable": true,
            "match_score": 20,
            "share_message": "Hey! Found this job: React Developer at ProLegion. Check it out!"
        }
    },
    {
        "id": "-5760693121534705945",
        "title": "UI/UX Designer (Figma Expert)",
        "company": "Gomahamaya",
        "location": "BR, IN",
        "date_posted": "2026-01-06",
        "found_at": "02:13",
        "job_url": "https://in.indeed.com/viewjob?jk=bea6bf33f37b13ef",
        "site": "indeed",
        "analysis": {
            "is_suitable": true,
            "match_score": 28,
            "share_message": "Hey! Found this job: UI/UX Designer (Figma Expert) at Gomahamaya. Check it out!"
        }
    },
    {
        "id": "-4104008477370873905",
        "title": "Full Stack Developer (Fresher)",
        "company": "Sioniq",
        "location": "KL, IN",
        "date_posted": "2026-01-06",
        "found_at": "02:13",
        "job_url": "https://in.indeed.com/viewjob?jk=132ce1dca3ce7cde",
        "site": "indeed",
        "analysis": {
            "is_suitable": true,
            "match_score": 77,
            "share_message": "Hey! Found this job: Full Stack Developer (Fresher) at Sioniq. Check it out!"
        }
    },
    {
        "id": "2011438845503962633",
        "title": "Full Stack Developer Intern",
        "company": "Accusoil Agri technologies PVT LTD",
        "location": "RJ, IN",
        "date_posted": "2026-01-06",
        "found_at": "02:13",
        "job_url": "https://in.indeed.com/viewjob?jk=70a9de8445067f42",
        "site": "indeed",
        "analysis": {
            "is_suitable": true,
            "match_score": 28,
            "share_message": "Hey! Found this job: Full Stack Developer Intern at Accusoil Agri technologies PVT LTD. Check it out!"
        }
    },
    {
        "id": "-6756423905586329510",
        "title": "AI-Augmented Software Developer (1-3 Years ) (Mumbai)",
        "company": "Wama Technology",
        "location": "MH, IN",
        "date_posted": "2026-01-06",
        "found_at": "02:13",
        "job_url": "https://in.indeed.com/viewjob?jk=925d0ed092cf659c",
        "site": "indeed",
        "analysis": {
            "is_suitable": true,
            "match_score": 57,
            "share_message": "Hey! Found this job: AI-Augmented Software Developer (1-3 Years ) (Mumbai) at Wama Technology. Check it out!"
        }
    },
    {
        "id": "-5733155466381728478",
        "title": "Assistant Full Stack Developer",
        "company": "EasyLauncher",
        "location": "UP, IN",
        "date_posted": "2026-01-06",
        "found_at": "02:13",
        "job_url": "https://in.indeed.com/viewjob?jk=cdc7cecd603387b2",
        "site": "indeed",
        "analysis": {
            "is_suitable": true,
            "match_score": 71,
            "share_message": "Hey! Found this job: Assistant Full Stack Developer at EasyLauncher. Check it out!"
        }
    },
    {
        "id": "-304393751225668021",
        "title": "Dot Net Developer",
        "company": "Ciya Technologies",
        "location": "OR, IN",
        "date_posted": "2026-01-06",
        "found_at": "02:13",
        "job_url": "https://in.indeed.com/viewjob?jk=252ad2b45a2c9b80",
        "site": "indeed",
        "analysis": {
            "is_suitable": true,
            "match_score": 57,
            "share_message": "Hey! Found this job: Dot Net Developer at Ciya Technologies. Check it out!"
        }
    },
    {
        "id": "3070487532743952744",
        "title": "PHP Laravel Developer",
        "company": "Jangras Corporation",
        "location": "HR, IN",
        "date_posted": "2026-01-06",
        "found_at": "02:13",
        "job_url": "https://in.indeed.com/viewjob?jk=27e15bfded0f6e78",
        "site": "indeed",
        "analysis": {
            "is_suitable": true,
            "match_score": 57,
            "share_message": "Hey! Found this job: PHP Laravel Developer at Jangras Corporation. Check it out!"
        }
    },
    {
        "id": "-2847235454223531655",
        "title": "Full Stack Python Developer",
        "company": "Hashtechy",
        "location": "GJ, IN",
        "date_posted": "2026-01-06",
        "found_at": "02:13",
        "job_url": "https://in.indeed.com/viewjob?jk=5d6ac5d4c0e5755c",
        "site": "indeed",
        "analysis": {
            "is_suitable": true,
            "match_score": 77,
            "share_message": "Hey! Found this job: Full Stack Python Developer at Hashtechy. Check it out!"
        }
    },
    {
        "id": "6270611546348830487",
        "title": ".NET Core Developer ( Experienced )",
        "company": "DB Vertex Technologies",
        "location": "MP, IN",
        "date_posted": "2026-01-06",
        "found_at": "02:13",
        "job_url": "https://in.indeed.com/viewjob?jk=a76e19ce935f20a1",
        "site": "indeed",
        "analysis": {
            "is_suitable": true,
            "match_score": 42,
            "share_message": "Hey! Found this job: .NET Core Developer ( Experienced ) at DB Vertex Technologies. Check it out!"
        }
    },
    {
        "id": "7423220124850414925",
        "title": "Software Dev Engineer I, Amazon University Talent Acquisition",
        "company": "Amazon.com",
        "location": "DL, IN",
        "date_posted": "2025-11-18",
        "found_at": "02:13",
        "job_url": "https://in.indeed.com/viewjob?jk=07a77e5dbf764d1b",
        "site": "indeed",
        "analysis": {
            "is_suitable": true,
            "match_score": 14,
            "share_message": "Hey! Found this job: Software Dev Engineer I, Amazon University Talent Acquisition at Amazon.com. Check it out!"
        }
    },
    {
        "id": "-3727674631747113247",
        "title": "Software Dev Engineer I, Amazon University Talent Acquisition",
        "company": "Amazon.com",
        "location": "TN, IN",
        "date_posted": "2025-11-18",
        "found_at": "02:13",
        "job_url": "https://in.indeed.com/viewjob?jk=627c73257c148c3c",
        "site": "indeed",
        "analysis": {
            "is_suitable": true,
            "match_score": 14,
            "share_message": "Hey! Found this job: Software Dev Engineer I, Amazon University Talent Acquisition at Amazon.com. Check it out!"
        }
    },
    {
        "id": "4702944993710459176",
        "title": "Software Dev Engineer I, Amazon University Talent Acquisition",
        "company": "Amazon.com",
        "location": "TS, IN",
        "date_posted": "2025-11-18",
        "found_at": "02:13",
        "job_url": "https://in.indeed.com/viewjob?jk=0bab7c9825ef4fa9",
        "site": "indeed",
        "analysis": {
            "is_suitable": true,
            "match_score": 14,
            "share_message": "Hey! Found this job: Software Dev Engineer I, Amazon University Talent Acquisition at Amazon.com. Check it out!"
        }
    },
    {
        "id": "-7763765403779341701",
        "title": "Software Dev Engineer I, Amazon University Talent Acquisition",
        "company": "Amazon.com",
        "location": "MH, IN",
        "date_posted": "2025-11-18",
        "found_at": "02:13",
        "job_url": "https://in.indeed.com/viewjob?jk=5cb234f27c30ad57",
        "site": "indeed",
        "analysis": {
            "is_suitable": true,
            "match_score": 14,
            "share_message": "Hey! Found this job: Software Dev Engineer I, Amazon University Talent Acquisition at Amazon.com. Check it out!"
        }
    },
    {
        "id": "-3845829845778092792",
        "title": "Software Dev Engineer I, Amazon University Talent Acquisition",
        "company": "Amazon.com",
        "location": "KA, IN",
        "date_posted": "2025-11-18",
        "found_at": "02:13",
        "job_url": "https://in.indeed.com/viewjob?jk=fc430075373f58a7",
        "site": "indeed",
        "analysis": {
            "is_suitable": true,
            "match_score": 14,
            "share_message": "Hey! Found this job: Software Dev Engineer I, Amazon University Talent Acquisition at Amazon.com. Check it out!"
        }
    },
    {
        "id": "-8199863469217926515",
        "title": "Software Dev Engineer I, Amazon University Talent Acquisition",
        "company": "Amazon.com",
        "location": "TS, IN",
        "date_posted": "2025-10-03",
        "found_at": "02:13",
        "job_url": "https://in.indeed.com/viewjob?jk=de64639c77d5d748",
        "site": "indeed",
        "analysis": {
            "is_suitable": true,
            "match_score": 14,
            "share_message": "Hey! Found this job: Software Dev Engineer I, Amazon University Talent Acquisition at Amazon.com. Check it out!"
        }
    }
]